tests/__init__.py
tests/test_all.py
xapres/__init__.py
xapres/load.py
xapres/utils.py
xapres-0.14.6.dist-info/LICENSE.txt
xapres-0.14.6.dist-info/METADATA
xapres-0.14.6.dist-info/WHEEL
xapres-0.14.6.dist-info/top_level.txt
xapres-0.14.6.dist-info/RECORD
