Metadata-Version: 2.2
Name: xapres
Version: 0.14.6
Summary: A package for processing data from the Autonomous phase-sensitive Radio-Echo Sounder (ApRES) using xarray.
Home-page: https://github.com/ldeo-glaciology/xapres
Author: ldeo_glaciology
Author-email: j.kingslake@columbia.edu
License: MIT
Classifier: Development Status :: 2 - Pre-Alpha
Classifier: Topic :: Scientific/Engineering
Classifier: Intended Audience :: Science/Research
Classifier: Operating System :: OS Independent
Classifier: Programming Language :: Python
Classifier: Programming Language :: Python :: 3
Classifier: Programming Language :: Python :: 3.6
Classifier: Programming Language :: Python :: 3.7
Classifier: Programming Language :: Python :: 3.8
Classifier: License :: OSI Approved :: MIT License
Requires-Python: >=3.6
License-File: LICENSE.txt
Requires-Dist: numpy
Requires-Dist: requests
Requires-Dist: xarray
Requires-Dist: gcsfs
Requires-Dist: fsspec
Requires-Dist: pandas
Requires-Dist: tqdm
Dynamic: author
Dynamic: author-email
Dynamic: classifier
Dynamic: description
Dynamic: description-content-type
Dynamic: home-page
Dynamic: license
Dynamic: requires-dist
Dynamic: requires-python
Dynamic: summary
